teritori/GCscript.py
teritori/GOscript.py
teritori/Motifs.py
teritori/__init__.py
teritori/final_pred.py
teritori/teritori.py
teritori/conserved_motifs/difmotifs.hmm
teritori/conserved_motifs/dnaaboxes.hmm
teritori-0.1.3.dist-info/LICENSE
teritori-0.1.3.dist-info/METADATA
teritori-0.1.3.dist-info/WHEEL
teritori-0.1.3.dist-info/entry_points.txt
teritori-0.1.3.dist-info/top_level.txt
teritori-0.1.3.dist-info/RECORD
