Metadata-Version: 2.1
Name: teritori
Version: 0.1.3
Summary: Replications origin and terminus prediction in bacterial genomes
Home-page: https://github.com/evolegiolab/findingori2
Author: Wiktor Gustafsson, Joakim Lindstrom, Ina Oden Osterbo
Author-email: teritori.team@gmail.com
License: GNU General Public License v3 or later (G  PLv3+)
Keywords: bioinformatics genomics replication
Platform: UNKNOWN
Classifier: Development Status :: 3 - Alpha
Classifier: Intended Audience :: Science/Research
Classifier: Topic :: Scientific/Engineering :: Bio-Informatics
Classifier: Environment :: Console
Classifier: License :: OSI Approved :: GNU General Public License v3 or later (GPLv3+)
Classifier: Programming Language :: Python :: 3
Classifier: Programming Language :: Python :: 3.6
Classifier: Programming Language :: Python :: 3.7
Requires-Dist: biopython
Requires-Dist: numpy
Requires-Dist: matplotlib
Requires-Dist: scipy
Requires-Dist: scikit-learn
Requires-Dist: bcbio-gff
